hist_pred_extractor/__init__.py
hist_pred_extractor/main.py
hist_pred_extractor/prompts.py
hist_pred_extractor-2025.12.21195029.dist-info/METADATA
hist_pred_extractor-2025.12.21195029.dist-info/WHEEL
hist_pred_extractor-2025.12.21195029.dist-info/top_level.txt
hist_pred_extractor-2025.12.21195029.dist-info/RECORD
