Metadata-Version: 2.4
Name: hist-pred-extractor
Version: 2025.12.21195029
Summary: Extracts & structures historical predictions from text using llmatch-messages.
Author-email: hist-pred-extractor <hi@eugene.plus>
License: MIT
Project-URL: Homepage, https://github.com/chigwell/hist-pred-extractor
Requires-Python: >=3.9
Requires-Dist: langchain-llm7>=0.0.0
Requires-Dist: llmatch-messages>=0.0.0
Requires-Dist: langchain-core>=0.3.0
